c7n_tencentcloud/__init__.py
c7n_tencentcloud/client.py
c7n_tencentcloud/entry.py
c7n_tencentcloud/output.py
c7n_tencentcloud/provider.py
c7n_tencentcloud/query.py
c7n_tencentcloud/utils.py
c7n_tencentcloud/actions/__init__.py
c7n_tencentcloud/actions/core.py
c7n_tencentcloud/actions/tags.py
c7n_tencentcloud/filters/__init__.py
c7n_tencentcloud/filters/metrics.py
c7n_tencentcloud/resources/__init__.py
c7n_tencentcloud/resources/ami.py
c7n_tencentcloud/resources/cam.py
c7n_tencentcloud/resources/cbs.py
c7n_tencentcloud/resources/cbs_snapshot.py
c7n_tencentcloud/resources/clb.py
c7n_tencentcloud/resources/cls.py
c7n_tencentcloud/resources/cos.py
c7n_tencentcloud/resources/cvm.py
c7n_tencentcloud/resources/dns_record.py
c7n_tencentcloud/resources/eip.py
c7n_tencentcloud/resources/elasticsearch.py
c7n_tencentcloud/resources/mysql.py
c7n_tencentcloud/resources/mysql_backup.py
c7n_tencentcloud/resources/nat_gateway.py
c7n_tencentcloud/resources/resource_map.py
c7n_tencentcloud/resources/security_group.py
c7n_tencentcloud/resources/subnet.py
c7n_tencentcloud/resources/tag.py
c7n_tencentcloud/resources/tcr.py
c7n_tencentcloud/resources/vpc.py
c7n_tencentcloud-0.1.31.dist-info/METADATA
c7n_tencentcloud-0.1.31.dist-info/WHEEL
c7n_tencentcloud-0.1.31.dist-info/RECORD
