Metadata-Version: 2.4
Name: c7n_tencentcloud
Version: 0.1.31
Summary: Cloud Custodian - Tencent Cloud Provider
Project-URL: Bug Tracker, https://github.com/cloud-custodian/cloud-custodian/issues
Project-URL: homepage, https://cloudcustodian.io
Project-URL: documentation, https://cloudcustodian.io/docs
Author: Tencent Cloud
License: Apache-2.0
Requires-Python: <4.0.0,>=3.9.2
Requires-Dist: c7n ==0.9.49
Requires-Dist: cos-python-sdk-v5 ==1.9.41
Requires-Dist: pytz ==2025.2
Requires-Dist: retrying ==1.4.2
Requires-Dist: tencentcloud-sdk-python ==3.1.31
